gen_msmask/__init__.py
gen_msmask/gen_mask.py
gen_msmask-2.0.0.dist-info/LICENSE
gen_msmask-2.0.0.dist-info/METADATA
gen_msmask-2.0.0.dist-info/WHEEL
gen_msmask-2.0.0.dist-info/entry_points.txt
gen_msmask-2.0.0.dist-info/top_level.txt
gen_msmask-2.0.0.dist-info/RECORD
