Metadata-Version: 2.1
Name: gen-msmask
Version: 2.0.0
Summary: A tool to generate masks for images of multispectrum
Author-email: Harishguna Satgunarajah <satgu7@gmail.com>, Saumik Khan <saumik.13@gmail.com>
Project-URL: Homepage, https://github.com/saumik13/multi-spectral-mask-generator
Project-URL: Bug Tracker, https://github.com/saumik13/multi-spectral-mask-generator
Classifier: Programming Language :: Python :: 3
Classifier: License :: OSI Approved :: MIT License
Classifier: Operating System :: OS Independent
Requires-Python: >=3.7
License-File: LICENSE
Requires-Dist: ipython (==8.7.0)
Requires-Dist: matplotlib (==3.5.1)
Requires-Dist: numpy (==1.23.5)
Requires-Dist: opencv-python (==4.6.0.66)
Requires-Dist: pandas (==1.4.1)
Requires-Dist: rembg (==2.0.29)
Requires-Dist: scikit-image (==0.19.3)
